101detect/detect.v
module detect(in, reset, clk, out);
    input in, clk, reset;
    output reg out;
    parameter s0 = 0, s1 = 1, s2 = 2, s3 = 3;
    reg [1:0] ps, ns;

    always@(posedge clk or posedge reset)
    begin
        if(reset)    ps <= s0;
        else         ps <= ns;
    end
    always@( ps, in)
        case (ps)
            s0 : begin
                    out = in ? 0 : 0;
                    ns = in ? s1 : s0;
                 end 
            s1 : begin
                    out = in ? 0 : 0;
                    ns = in ? s1 : s2;
                 end
            s2 : begin
                    out = in ? 1 : 0;
                    ns = in ? s3 : s0;
                 end
            s3 : begin
                    out = in ? 0 : 0;
                    ns = in ? s1 : s2;
                 end
        endcase
endmodule
c
module tb;
    reg in, clk, reset;
    wire out;
    detect D(in, reset, clk, out);
    initial
    begin
        $dumpfile("detect.vcd");
        $dumpvars(0,tb);
        clk = 1'b0;
        reset = 1'b1;
        #15 reset = 1'b0;
    end

    always #5 clk = ~clk;

    initial
    begin
        $monitor(in," ", out," ", clk); 
        #12 in = 0;
        #10 in = 1;
        #10 in = 1;
        #10 in = 1;
        #10 in = 1; #10 in = 1; #10 in = 0; #10 in = 0; #10 in = 1; #10 in = 1; #10 in = 0; #10 in = 1; #10 in = 0;
        
        #100 $finish;
    end
endmodule

101detect/detect.vcd
$date
	Tue Aug 23 15:33:30 2022
$end
$version
	Icarus Verilog
$end
$timescale
	1s
$end
$scope module tb $end
$var wire 1 ! out $end
$var reg 1 " clk $end
$var reg 1 # in $end
$var reg 1 $ reset $end
$scope module D $end
$var wire 1 " clk $end
$var wire 1 # in $end
$var wire 1 $ reset $end
$var parameter 32 % s0 $end
$var parameter 32 & s1 $end
$var parameter 32 ' s2 $end
$var parameter 32 ( s3 $end
$var reg 2 ) ns [1:0] $end
$var reg 1 ! out $end
$var reg 2 * ps [1:0] $end
$upscope $end
$upscope $end
$enddefinitions $end
$comment Show the parameter values. $end
$dumpall
b11 (
b10 '
b1 &
b0 %
$end
#0
$dumpvars
b0 *
b0x )
1$
x#
0"
0!
$end
#5
1"
#10
0"
#12
b0 )
0#
#15
1"
0$
#20
0"
#22
b1 )
1#
#25
b1 *
1"
#30
0"
#35
1"
#40
0"
#45
1"
#50
0"
#55
1"
#60
0"
#65
1"
#70
0"
#72
b10 )
0#
#75
b0 )
b10 *
1"
#80
0"
#85
b0 *
1"
#90
0"
#92
b1 )
1#
#95
b1 *
1"
#100
0"
#105
1"
#110
0"
#112
b10 )
0#
#115
b0 )
b10 *
1"
#120
0"
#122
b11 )
1!
1#
#125
b1 )
0!
b11 *
1"
#130
0"
#132
b10 )
0#
#135
b0 )
b10 *
1"
#140
0"
#145
b0 *
1"
